adafruit_veml6075.py
adafruit_circuitpython_veml6075-1.1.23.dist-info/licenses/LICENSE
adafruit_circuitpython_veml6075-1.1.23.dist-info/METADATA
adafruit_circuitpython_veml6075-1.1.23.dist-info/WHEEL
adafruit_circuitpython_veml6075-1.1.23.dist-info/top_level.txt
adafruit_circuitpython_veml6075-1.1.23.dist-info/RECORD
